slap/core/cli/__init__.py
slap/core/cli/app.py
slap/core/cli/argparse.py
slap/core/cli/command.py
slap/core/cli/completion.py
slap/core/cli/features.py
slap/core/cli/py.typed
slap/core/cli/typed.py
slap/core/cli/utils.py
slap.core.cli-0.3.1.dist-info/LICENSE
slap.core.cli-0.3.1.dist-info/WHEEL
slap.core.cli-0.3.1.dist-info/METADATA
slap.core.cli-0.3.1.dist-info/RECORD
