Metadata-Version: 2.1
Name: slap.core.cli
Version: 0.3.1
Summary: Extension of `argparse` to provide fast and customizable argument parsing.
License: MIT
Author: Niklas Rosenstein
Author-email: rosensteinniklas@gmail.com
Requires-Python: >=3.7,<4.0
Classifier: License :: OSI Approved :: MIT License
Classifier: Programming Language :: Python :: 3
Classifier: Programming Language :: Python :: 3.7
Classifier: Programming Language :: Python :: 3.8
Classifier: Programming Language :: Python :: 3.9
Classifier: Programming Language :: Python :: 3.10
Requires-Dist: nr.util (>=0.8.11,<0.9.0)
Requires-Dist: termcolor (>=1.1.0,<2.0.0)
Requires-Dist: typeapi (>=0.2.0,<0.3.0)
Project-URL: Bug Tracker, https://github.com/python-slap/slap.core.cli/issues
Project-URL: Repository, https://github.com/python-slap/slap.core.cli
